<?xml version="1.0" encoding="UTF-8"?><record_update table="question_choice">
    <question_choice action="INSERT_OR_UPDATE">
        <misc>0</misc>
        <order>12</order>
        <question display_value="Task">3c964c26dbccbc5061702c86059619bd</question>
        <rec_misc>0</rec_misc>
        <sys_class_name>question_choice</sys_class_name>
        <sys_created_by>dan.munk</sys_created_by>
        <sys_created_on>2021-05-13 18:25:28</sys_created_on>
        <sys_id>05968c26dbccbc5061702c8605961941</sys_id>
        <sys_mod_count>0</sys_mod_count>
        <sys_name>Conflict Check</sys_name>
        <sys_package display_value="Admin Support" source="x_paha_admin_suppo">ffb5fa661b3820105bf88777dc4bcb68</sys_package>
        <sys_policy/>
        <sys_scope display_value="Admin Support">ffb5fa661b3820105bf88777dc4bcb68</sys_scope>
        <sys_update_name>question_choice_05968c26dbccbc5061702c8605961941</sys_update_name>
        <sys_updated_by>dan.munk</sys_updated_by>
        <sys_updated_on>2021-05-13 18:25:28</sys_updated_on>
        <text>Conflict Check</text>
        <value>conflict_check</value>
    </question_choice>
    <fx_price action="delete_multiple" query="id=05968c26dbccbc5061702c8605961941"/>
    <fx_price action="INSERT_OR_UPDATE">
        <amount>0</amount>
        <currency display_value="USD">USD</currency>
        <field>misc</field>
        <id>05968c26dbccbc5061702c8605961941</id>
        <parent/>
        <reference_amount>0</reference_amount>
        <reference_currency display_value="USD">USD</reference_currency>
        <sys_created_by>dan.munk</sys_created_by>
        <sys_created_on>2021-05-13 18:25:28</sys_created_on>
        <sys_id>45968c26dbccbc5061702c8605961942</sys_id>
        <sys_mod_count>0</sys_mod_count>
        <sys_updated_by>dan.munk</sys_updated_by>
        <sys_updated_on>2021-05-13 18:25:28</sys_updated_on>
        <table>question_choice</table>
        <type>calculated</type>
    </fx_price>
    <fx_price action="INSERT_OR_UPDATE">
        <amount>0</amount>
        <currency display_value="USD">USD</currency>
        <field>rec_misc</field>
        <id>05968c26dbccbc5061702c8605961941</id>
        <parent/>
        <reference_amount>0</reference_amount>
        <reference_currency display_value="USD">USD</reference_currency>
        <sys_created_by>dan.munk</sys_created_by>
        <sys_created_on>2021-05-13 18:25:28</sys_created_on>
        <sys_id>0d968c26dbccbc5061702c8605961941</sys_id>
        <sys_mod_count>0</sys_mod_count>
        <sys_updated_by>dan.munk</sys_updated_by>
        <sys_updated_on>2021-05-13 18:25:28</sys_updated_on>
        <table>question_choice</table>
        <type>calculated</type>
    </fx_price>
</record_update>
